jupynium/__init__.py
jupynium/__main__.py
jupynium/buffer.py
jupynium/definitions.py
jupynium/events_control.py
jupynium/ipynb.py
jupynium/jupyter_notebook_selenium.py
jupynium/nvim.py
jupynium/process.py
jupynium/pynvim_helpers.py
jupynium/rpc_messages.py
jupynium/selenium_helpers.py
jupynium/cmds/__init__.py
jupynium/cmds/ipynb2jupytext.py
jupynium/cmds/jupynium.py
jupynium/js/get_cell_inputs.js
jupynium/js/kernel_complete.js
jupynium/js/kernel_inspect.js
jupynium/js/set_cell_text.js
jupynium/js/update_cell_selection.js
jupynium/lua/autocmd_vimleave.lua
jupynium/lua/cmp.lua
jupynium/lua/commands.lua
jupynium/lua/defaults.lua
jupynium/lua/helpers.lua
jupynium/lua/notify.lua
jupynium/_version.py
jupynium-0.2.7.dist-info/METADATA
jupynium-0.2.7.dist-info/WHEEL
jupynium-0.2.7.dist-info/entry_points.txt
jupynium-0.2.7.dist-info/licenses/LICENSE
jupynium-0.2.7.dist-info/RECORD
