Metadata-Version: 2.4
Name: jupynium
Version: 0.2.7
Summary: Neovim plugin that automates Jupyter Notebook editing/browsing using Selenium.
Project-URL: Homepage, https://github.com/kiyoon/jupynium.nvim
Author: Kiyoon Kim
License: MIT License
License-File: LICENSE
Keywords: jupyter,jupyter-notebook,neovim,neovim-plugin,nvim,nvim-plugin,selenium,vim
Classifier: License :: OSI Approved :: MIT License
Classifier: Programming Language :: Python
Classifier: Programming Language :: Python :: 3
Classifier: Programming Language :: Python :: 3.9
Classifier: Programming Language :: Python :: 3.10
Classifier: Programming Language :: Python :: 3.11
Classifier: Programming Language :: Python :: 3.12
Classifier: Programming Language :: Python :: 3.13
Classifier: Programming Language :: Python :: 3.14
Requires-Python: >=3.9
Requires-Dist: coloredlogs>=15.0.0
Requires-Dist: gitpython>=3.1.24
Requires-Dist: persist-queue>=0.8.0
Requires-Dist: platformdirs>=4.0.0
Requires-Dist: psutil>=5.9.4
Requires-Dist: pynvim>=0.5.0
Requires-Dist: selenium>=4.7.2
Requires-Dist: verboselogs>=1.7
Provides-Extra: dev
Requires-Dist: pytest-cov>=5.0.0; extra == 'dev'
Requires-Dist: pytest>=8.0.0; extra == 'dev'
Requires-Dist: ruff==0.9.6; extra == 'dev'
Requires-Dist: tox>=4.19.0; extra == 'dev'
Requires-Dist: version-pioneer; extra == 'dev'
